adios/__init__.py
adios/despedidas.py
hola/__init__.py
hola/saludos.py
tests/__init__.py
tests/test_hola.py
Mensajes_keviruii-3.0.dist-info/LICENSE
Mensajes_keviruii-3.0.dist-info/METADATA
Mensajes_keviruii-3.0.dist-info/WHEEL
Mensajes_keviruii-3.0.dist-info/top_level.txt
Mensajes_keviruii-3.0.dist-info/RECORD
