Metadata-Version: 2.1
Name: Mensajes-keviruii
Version: 3.0
Summary: Un paquete para saludar y despedir
Home-page: http://hcosta.info
Author: Kevin Ruiz
Author-email: kevinagustinrockz@gmail.com
Classifier: Environment :: Console
Classifier: Intended Audience :: Developers
Classifier: Programming Language :: Python
Classifier: Topic :: Utilities
License-File: LICENSE
Requires-Dist: numpy (>=1.23.0)
